<?xml version="1.0" encoding="utf-8" ?><dwsync><file name="jquery.debouncedresize.js" server="www.djburn.com//" local="3554915484" remote="319783739199405748" Dst="-1" /><file name="comment-reply.min.js" server="www.djburn.com//" local="3554915456" remote="319783739199405748" Dst="-1" /><file name="jquery.countupcircle.js" server="www.djburn.com//" local="3554915482" remote="319783739199405748" Dst="-1" /><file name="cherry-plugin.js" server="www.djburn.com//" local="3554915442" remote="319783739199405748" Dst="-1" /><file name="jflickrfeed.js" server="www.djburn.com//" local="3554915462" remote="319783739199405748" Dst="-1" /><file name="jquery.ba-resize.min.js" server="www.djburn.com//" local="3554915478" remote="319783739199405748" Dst="-1" /><file name="utilits.js" server="www.djburn.com//" local="3554915518" remote="319783739199405748" Dst="-1" /><file name="jquery.mousewheel-3.0.4.js" server="www.djburn.com//" local="3554915504" remote="319783739199405748" Dst="-1" /><file name="jquery.mobilemenu.js" server="www.djburn.com//" local="3554915502" remote="319783739199405748" Dst="-1" /><file name="tmstickup.js" server="www.djburn.com//" local="3554915516" remote="319783739199405748" Dst="-1" /><file name="cherry.lazy-load.js" server="www.djburn.com//" local="3554915442" remote="319783739199405748" Dst="-1" /><file name="device.min.js" server="www.djburn.com//" local="3554915460" remote="319783739199405748" Dst="-1" /><file name="superfish.js" server="www.djburn.com//" local="3554915512" remote="319783739199405748" Dst="-1" /><file name="cherry.parallax.js" server="www.djburn.com//" local="3554915446" remote="319783739199405748" Dst="-1" /><file name="jquery.easing.1.3.js" server="www.djburn.com//" local="3554915484" remote="319783739199405748" Dst="-1" /><file name="cv_script.js" server="www.djburn.com//" local="3554915460" remote="319783739199405748" Dst="-1" /><file name="jquery-migrate-1.2.1.min.js" server="www.djburn.com//" local="3554915474" remote="319783739199405748" Dst="-1" /><file name="custom.js" server="www.djburn.com//" local="3554915458" remote="319783739199405748" Dst="-1" /><file name="theme_script.js" server="www.djburn.com//" local="3554915516" remote="319783739199405748" Dst="-1" /><file name="jplayer.playlist.min.js" server="www.djburn.com//" local="3554915468" remote="319783739199405748" Dst="-1" /><file name="scripts.js" server="www.djburn.com//" local="3554915510" remote="319783739199405748" Dst="-1" /><file name="swfobject.js" server="www.djburn.com//" local="3554915514" remote="319783739199405748" Dst="-1" /><file name="jquery.zaccordion.min.js" server="www.djburn.com//" local="3554915506" remote="319783739199405748" Dst="-1" /><file name="modernizr.js" server="www.djburn.com//" local="3554915506" remote="319783739199405748" Dst="-1" /><file name="jquery.isotope.js" server="www.djburn.com//" local="3554915490" remote="319783739199405748" Dst="-1" /><file name="jquery.form.min.js" server="www.djburn.com//" local="3554915488" remote="319783739199405748" Dst="-1" /><file name="cherry_media_parallax.js" server="www.djburn.com//" local="3554915452" remote="319783739199405748" Dst="-1" /><file name="jquery.mobile.customized.min.js" server="www.djburn.com//" local="3554915500" remote="319783739199405748" Dst="-1" /><file name="chart.min.js" server="www.djburn.com//" local="3554915440" remote="319783739199405748" Dst="-1" /><file name="jquery.magnific-popup.min.js" server="www.djburn.com//" local="3554915498" remote="319783739199405748" Dst="-1" /><file name="jquery.flexslider-min.js" server="www.djburn.com//" local="3554915486" remote="319783739199405748" Dst="-1" /><file name="owl.carousel.min.js" server="www.djburn.com//" local="3554915508" remote="319783739199405748" Dst="-1" /><file name="camera.min.js" server="www.djburn.com//" local="3554915436" remote="319783739199405748" Dst="-1" /><file name="jquery.jplayer.min.js" server="www.djburn.com//" local="3554915496" remote="319783739199405748" Dst="-1" /><file name="jquery-1.7.2.min.js" server="www.djburn.com//" local="3554915472" remote="319783739199405748" Dst="-1" /></dwsync>